Metadata-Version: 2.1
Name: william-chromedriver-manager
Version: 0.0.3
Summary: 根据Chrome浏览器版本下载对应的webdriver
Home-page: https://github.com/fengzhaoxi/william_chromedriver_manager
Author: ZhaoXi Feng
Author-email: fengzx120@gmail.com
License: UNKNOWN
Platform: UNKNOWN
License-File: LICENSE
